README.rst
setup.py
nginxparser/__init__.py
nginxparser/core.py
nginxparser/patterns.py
nginxparser.egg-info/PKG-INFO
nginxparser.egg-info/SOURCES.txt
nginxparser.egg-info/dependency_links.txt
nginxparser.egg-info/entry_points.txt
nginxparser.egg-info/top_level.txt