Metadata-Version: 1.1
Name: nginxparser
Version: 1.0.0
Summary: Nginx log parser and analyzer
Home-page: https://github.com/xtimon/nginxparser
Author: Timur Isanov
Author-email: tisanov@yahoo.com
License: MIT
Platform: UNKNOWN
Classifier: Topic :: Internet :: Log Analysis
Classifier: License :: OSI Approved :: MIT License
Classifier: Programming Language :: Python :: 2
Classifier: Programming Language :: Python :: 2.7
Classifier: Programming Language :: Python :: 3
Classifier: Programming Language :: Python :: 3.3
Classifier: Programming Language :: Python :: 3.4
Classifier: Programming Language :: Python :: 3.5
